[
  {
    "id": 1,
    "imageSrc": "./assets/images/product1.png",
    "title": "Margherita Pizza",
    "price": "₹199",
    "rating": "4.5",
    "time": "25-30 min",
    "percentageOff": "10%"
  },
  {
    "id": 2,
    "imageSrc": "./assets/images/product2.png",
    "title": "Farmhouse Pizza",
    "price": "₹299",
    "rating": "4.6",
    "time": "30-35 min"
  },
  {
    "id": 3,
    "imageSrc": "./assets/images/product3.png",
    "title": "Pepperoni Pizza",
    "price": "₹349",
    "rating": "4.7",
    "time": "30-40 min",
    "percentageOff": "15%"
  },
  {
    "id": 4,
    "imageSrc": "./assets/images/product4.png",
    "title": "Veggie Supreme Pizza",
    "price": "₹279",
    "rating": "4.4",
    "time": "25-35 min"
  },
  {
    "id": 5,
    "imageSrc": "./assets/images/product5.png",
    "title": "Cheese Burst Pizza",
    "price": "₹249",
    "rating": "4.8",
    "time": "20-30 min",
    "percentageOff": "20%"
  },
  {
    "id": 6,
    "imageSrc": "./assets/images/product2.png",
    "title": "BBQ Chicken Pizza",
    "price": "₹399",
    "rating": "4.5",
    "time": "30-40 min",
    "percentageOff": "12%"
  },
  {
    "id": 7,
    "imageSrc": "./assets/images/product3.png",
    "title": "Paneer Tikka Pizza",
    "price": "₹329",
    "rating": "4.6",
    "time": "25-35 min"
  },
  {
    "id": 8,
    "imageSrc": "./assets/images/product4.png",
    "title": "Mexican Green Wave Pizza",
    "price": "₹289",
    "rating": "4.3",
    "time": "30-40 min",
    "percentageOff": "18%"
  },
  {
    "id": 9,
    "imageSrc": "./assets/images/product1.png",
    "title": "Classic Italian Pizza",
    "price": "₹319",
    "rating": "4.6",
    "time": "25-30 min"
  },
  {
    "id": 10,
    "imageSrc": "./assets/images/product2.png",
    "title": "Double Cheese Pizza",
    "price": "₹269",
    "rating": "4.5",
    "time": "20-25 min",
    "percentageOff": "10%"
  },
  {
    "id": 11,
    "imageSrc": "./assets/images/product3.png",
    "title": "Tandoori Chicken Pizza",
    "price": "₹429",
    "rating": "4.7",
    "time": "35-45 min"
  },
  {
    "id": 12,
    "imageSrc": "./assets/images/product4.png",
    "title": "Spicy Peri Peri Pizza",
    "price": "₹309",
    "rating": "4.4",
    "time": "25-35 min",
    "percentageOff": "22%"
  }
]
